Metadata-Version: 2.1
Name: head_controller
Version: 1.1.2
Summary: A package to quickly train and predict head gestures
Home-page: https://github.com/nightvision04/simple-gesture-tracking
Author: Dan Scott
Author-email: danscottlearns@gmail.com
License: UNKNOWN
Keywords: head,controller,nueral net,movement,axis,recognition,computer vision,head tracking
Platform: UNKNOWN
Classifier: Development Status :: 4 - Beta
Classifier: Intended Audience :: Developers
Classifier: Topic :: Software Development :: Build Tools
Classifier: License :: OSI Approved :: MIT License
Classifier: Programming Language :: Python :: 3.7
Classifier: Operating System :: OS Independent
